django_memcached_hashring-0.1.2.dist-info/DESCRIPTION.rst
django_memcached_hashring-0.1.2.dist-info/METADATA
django_memcached_hashring-0.1.2.dist-info/pydist.json
django_memcached_hashring-0.1.2.dist-info/RECORD
django_memcached_hashring-0.1.2.dist-info/top_level.txt
django_memcached_hashring-0.1.2.dist-info/WHEEL
memcached_hashring/__init__.py
memcached_hashring/backend.py
memcached_hashring/client.py
