Metadata-Version: 2.0
Name: django-memcached-hashring
Version: 0.1.2
Summary: A Django cache backend for Memcached with consistent consistent hashing.
Home-page: http://github.com/jezdez/django-memcached-hashring
Author: Jannis Leidel
Author-email: jannis@leidel.info
License: BSD
Platform: UNKNOWN
Classifier: Development Status :: 4 - Beta
Classifier: Framework :: Django
Classifier: Intended Audience :: Developers
Classifier: License :: OSI Approved :: BSD License
Classifier: Operating System :: OS Independent
Classifier: Programming Language :: Python
Classifier: Programming Language :: Python :: 2.6
Classifier: Programming Language :: Python :: 2.7
Classifier: Topic :: Utilities
Requires-Dist: python-memcached
Requires-Dist: hash-ring
